{
  "started_at": "2026-04-22 18:32:16",
  "finished_at": null,
  "dry_run": false,
  "force": false,
  "mode": "overwrite",
  "total": 845,
  "processed": 286,
  "verified": 244,
  "patched": 238,
  "unchanged": 6,
  "failed": 27,
  "low_confidence": 14,
  "not_found": 14,
  "elapsed_sec": 5086.8,
  "eta_sec": 9942.4,
  "by_phase": {
    "kkaku": {
      "total": 158,
      "processed": 158,
      "patched": 156,
      "not_found": 0,
      "failed": 0
    },
    "office": {
      "total": 37,
      "processed": 37,
      "patched": 19,
      "not_found": 14,
      "failed": 0
    },
    "sh": {
      "total": 650,
      "processed": 91,
      "patched": 63,
      "not_found": 0,
      "failed": 27
    }
  },
  "current": {
    "phase": "sh",
    "patched": false,
    "idx": 286,
    "key": "NOBUNAGAキャピタルビレッジ株式会社",
    "verified": false
  },
  "recent": [
    {
      "status": "ok",
      "phase": "sh",
      "action": "patched",
      "key": "岐阜県立飛騨高山高等学校",
      "notion_url": "https://www.notion.so/345aa45a3f138153b4dbd71a8268cb10",
      "note": "9項目"
    },
    {
      "status": "error",
      "phase": "sh",
      "key": "株式会社 Otono",
      "note": "APIResponseError: Invalid multi_select option, commas not allowed: 観光IT, 音声コンテンツ制作"
    },
    {
      "status": "error",
      "phase": "sh",
      "key": "株式会社 地域資源バンクNIU",
      "note": "APIResponseError: Invalid multi_select option, commas not allowed: 地域資源プロデュース, サイクルツーリズム, まちづくり"
    },
    {
      "status": "ok",
      "phase": "sh",
      "action": "patched",
      "key": "うらかた屋",
      "notion_url": "https://www.notion.so/349aa45a3f1381a7a87cf40264b93ff5",
      "note": "10項目"
    },
    {
      "status": "ok",
      "phase": "sh",
      "action": "patched",
      "key": "株式会社eiicon",
      "notion_url": "https://www.notion.so/eiicon-346aa45a3f138107a6c5d6adf9f7c196",
      "note": "9項目"
    },
    {
      "status": "ok",
      "phase": "sh",
      "action": "patched",
      "key": "日本政策金融公庫",
      "notion_url": "https://www.notion.so/349aa45a3f1381bab08df58d1062366c",
      "note": "10項目"
    },
    {
      "status": "error",
      "phase": "sh",
      "key": "株式会社 日経BP",
      "note": "APIResponseError: Invalid multi_select option, commas not allowed: 出版, メディア"
    },
    {
      "status": "ok",
      "phase": "sh",
      "action": "patched",
      "key": "イエロ株式会社",
      "notion_url": "https://www.notion.so/345aa45a3f1381c4b32fc8b5780a5a8d",
      "note": "10項目"
    },
    {
      "status": "ok",
      "phase": "sh",
      "action": "patched",
      "key": "NPO法人 タダカヨ",
      "notion_url": "https://www.notion.so/NPO-345aa45a3f138190815bf551d8605b27",
      "note": "10項目"
    },
    {
      "status": "ok",
      "phase": "sh",
      "action": "patched",
      "key": "パーソル キャリア 株式会社",
      "notion_url": "https://www.notion.so/349aa45a3f13811ea74ed5d54fd39b00",
      "note": "10項目"
    },
    {
      "status": "ok",
      "phase": "sh",
      "action": "patched",
      "key": "刈谷市役所",
      "notion_url": "https://www.notion.so/345aa45a3f1381d99975d979077f45d8",
      "note": "10項目"
    },
    {
      "status": "ok",
      "phase": "sh",
      "action": "patched",
      "key": "参議院事務局",
      "notion_url": "https://www.notion.so/346aa45a3f13818183b2f594ad09a914",
      "note": "10項目"
    },
    {
      "status": "ok",
      "phase": "sh",
      "action": "patched",
      "key": "Venture Café Tokyo",
      "notion_url": "https://www.notion.so/Venture-Caf-Tokyo-349aa45a3f1381fc9ad6d6763358e8b9",
      "note": "10項目"
    },
    {
      "status": "error",
      "phase": "sh",
      "key": "STATION Ai 株式会社",
      "note": "APIResponseError: Invalid multi_select option, commas not allowed: スタートアップ支援, オープンイノベーション"
    },
    {
      "status": "ok",
      "phase": "sh",
      "action": "patched",
      "key": "地域と人と未来株式会社",
      "notion_url": "https://www.notion.so/345aa45a3f1381f783c1e90bf576e5e2",
      "note": "9項目"
    },
    {
      "status": "ok",
      "phase": "sh",
      "action": "patched",
      "key": "Theta Times Ventures",
      "notion_url": "https://www.notion.so/Theta-Times-Ventures-349aa45a3f13817fbbcbe910dbad5cb5",
      "note": "8項目"
    },
    {
      "status": "ok",
      "phase": "sh",
      "action": "patched",
      "key": "中部ニュービジネス協議会",
      "notion_url": "https://www.notion.so/345aa45a3f138169b2adeee4c7c56125",
      "note": "9項目"
    },
    {
      "status": "error",
      "phase": "sh",
      "key": "株式会社IMOM",
      "note": "APIResponseError: Invalid multi_select option, commas not allowed: 就労支援, 飲食コンサルティング, カフェ運営"
    },
    {
      "status": "ok",
      "phase": "sh",
      "action": "patched",
      "key": "株式会社 QUICK",
      "notion_url": "https://www.notion.so/QUICK-349aa45a3f13819e90c7d21d354af950",
      "note": "9項目"
    },
    {
      "status": "error",
      "phase": "sh",
      "key": "I'mbesideyou Inc.",
      "note": "APIResponseError: Invalid multi_select option, commas not allowed: AI開発, コンサルティング"
    },
    {
      "status": "error",
      "phase": "sh",
      "key": "城南法律事務所",
      "note": "APIResponseError: Invalid multi_select option, commas not allowed: 法律事務所, 弁理士業"
    },
    {
      "status": "ok",
      "phase": "sh",
      "action": "patched",
      "key": "株式会社 クリエイティブ ネクサス",
      "notion_url": "https://www.notion.so/349aa45a3f1381f0aff4dafa8feefa6c",
      "note": "10項目"
    },
    {
      "status": "ok",
      "phase": "sh",
      "action": "patched",
      "key": "城南国際特許事務所",
      "notion_url": "https://www.notion.so/347aa45a3f13819a80ecfcae48079a2d",
      "note": "9項目"
    },
    {
      "status": "error",
      "phase": "sh",
      "key": "株式会社HERITAGE",
      "note": "APIResponseError: Invalid multi_select option, commas not allowed: 出版, Webメディア"
    },
    {
      "status": "error",
      "phase": "sh",
      "key": "社会保険労務士法人 ふたば",
      "note": "APIResponseError: Invalid multi_select option, commas not allowed: 社会保険労務士, 労務コンサルティング"
    },
    {
      "status": "ok",
      "phase": "sh",
      "action": "patched",
      "key": "シンニチ互業株式会社",
      "notion_url": "https://www.notion.so/349aa45a3f1381328531f54df59486c9",
      "note": "10項目"
    },
    {
      "status": "ok",
      "phase": "sh",
      "action": "patched",
      "key": "愛知県中小企業青年中央会",
      "notion_url": "https://www.notion.so/349aa45a3f1381048feac4a6df9f373f",
      "note": "10項目"
    },
    {
      "status": "ok",
      "phase": "sh",
      "action": "patched",
      "key": "一般社団法人ものづくりパートナーズ",
      "notion_url": "https://www.notion.so/345aa45a3f13818e8f96c6094a6e63c7",
      "note": "10項目"
    },
    {
      "status": "ok",
      "phase": "sh",
      "action": "patched",
      "key": "大矢伝動精機株式会社",
      "notion_url": "https://www.notion.so/349aa45a3f13814daffae076f05b6745",
      "note": "10項目"
    },
    {
      "status": "ok",
      "phase": "sh",
      "action": "patched",
      "key": "株式会社中島商店",
      "notion_url": "https://www.notion.so/346aa45a3f1381fe9f8cfd3d8dfe7be1",
      "note": "10項目"
    },
    {
      "status": "ok",
      "phase": "sh",
      "action": "patched",
      "key": "株式会社XLOCAL",
      "notion_url": "https://www.notion.so/XLOCAL-349aa45a3f13811a85b2df604a828aae",
      "note": "10項目"
    },
    {
      "status": "error",
      "phase": "sh",
      "key": "株式会社Brownie",
      "note": "APIResponseError: Invalid multi_select option, commas not allowed: AI開発, アプリ開発, DXコンサル"
    },
    {
      "status": "ok",
      "phase": "sh",
      "action": "patched",
      "key": "株式会社 三辻商店",
      "notion_url": "https://www.notion.so/346aa45a3f13818da241f5b5358c6548",
      "note": "9項目"
    },
    {
      "status": "error",
      "phase": "sh",
      "key": "STUDIO POLAR/S",
      "note": "APIResponseError: Invalid multi_select option, commas not allowed: アニメーション制作, 出版"
    },
    {
      "status": "ok",
      "phase": "sh",
      "action": "patched",
      "key": "131kR acycle",
      "notion_url": "https://www.notion.so/131kR-acycle-349aa45a3f1381abbe7fdfb40e9c9fcf",
      "note": "10項目"
    },
    {
      "status": "error",
      "phase": "sh",
      "key": "100BANCH",
      "note": "APIResponseError: Invalid multi_select option, commas not allowed: 未来創造支援, コミュニティ運営"
    },
    {
      "status": "ok",
      "phase": "sh",
      "action": "patched",
      "key": "雷山高専",
      "notion_url": "https://www.notion.so/349aa45a3f1381ed8fe1ffc8226fa356",
      "note": "2項目"
    },
    {
      "status": "ok",
      "phase": "sh",
      "action": "patched",
      "key": "富山高専専本郷キャンパス",
      "notion_url": "https://www.notion.so/349aa45a3f13816aa3cccf38662e4b93",
      "note": "10項目"
    },
    {
      "status": "ok",
      "phase": "sh",
      "action": "patched",
      "key": "呉工業高等専門学校",
      "notion_url": "https://www.notion.so/349aa45a3f13817088dad2ce9562323d",
      "note": "9項目"
    },
    {
      "status": "error",
      "phase": "sh",
      "key": "株式会社 Tol Nexus",
      "note": "APIResponseError: Invalid multi_select option, commas not allowed: AI開発, コンサルティング"
    },
    {
      "status": "error",
      "phase": "sh",
      "key": "クウジット株式会社",
      "note": "APIResponseError: Invalid multi_select option, commas not allowed: AI開発, システム開発"
    },
    {
      "status": "ok",
      "phase": "sh",
      "action": "patched",
      "key": "NECソリューションイノベータ株式会社",
      "notion_url": "https://www.notion.so/NEC-345aa45a3f1381578a58fb6d5e89e783",
      "note": "10項目"
    },
    {
      "status": "error",
      "phase": "sh",
      "key": "株式会社 セブン＆アイ・ネットメディア",
      "note": "APIResponseError: Invalid multi_select option, commas not allowed: システム開発, ITサービス"
    },
    {
      "status": "ok",
      "phase": "sh",
      "action": "patched",
      "key": "東京大学",
      "notion_url": "https://www.notion.so/349aa45a3f138173b1c0f008bf571858",
      "note": "10項目"
    },
    {
      "status": "ok",
      "phase": "sh",
      "action": "patched",
      "key": "日本ガイシ株式会社",
      "notion_url": "https://www.notion.so/349aa45a3f1381009de0f9f70cb8e0fe",
      "note": "10項目"
    },
    {
      "status": "ok",
      "phase": "sh",
      "action": "patched",
      "key": "日本電技株式会社",
      "notion_url": "https://www.notion.so/345aa45a3f1381669fd7d0f1dae1ba90",
      "note": "10項目"
    },
    {
      "status": "ok",
      "phase": "sh",
      "action": "patched",
      "key": "株式会社テレビ朝日",
      "notion_url": "https://www.notion.so/345aa45a3f13815e898bdb5afc5cae1d",
      "note": "10項目"
    },
    {
      "status": "ok",
      "phase": "sh",
      "action": "patched",
      "key": "東京大学大学院",
      "notion_url": "https://www.notion.so/349aa45a3f13811fb197ec79e1ef0896",
      "note": "10項目"
    },
    {
      "status": "ok",
      "phase": "sh",
      "action": "patched",
      "key": "株式会社松尾研究所",
      "notion_url": "https://www.notion.so/345aa45a3f138163b626c1455ac500e1",
      "note": "9項目"
    },
    {
      "status": "error",
      "phase": "sh",
      "key": "株式会社ワイズ",
      "note": "APIResponseError: Invalid multi_select option, commas not allowed: ITソリューション, OA機器販売"
    }
  ]
}